isabl_cli/VERSION
isabl_cli/__init__.py
isabl_cli/__main__.py
isabl_cli/api.py
isabl_cli/app.py
isabl_cli/cli.py
isabl_cli/commands.py
isabl_cli/data.py
isabl_cli/exceptions.py
isabl_cli/factories.py
isabl_cli/options.py
isabl_cli/settings.py
isabl_cli/signals.py
isabl_cli/utils.py
isabl_cli/validators.py
isabl_cli/batch_systems/__init__.py
isabl_cli/batch_systems/local.py
isabl_cli/batch_systems/lsf.py
isabl_cli/batch_systems/sge.py
isabl_cli/batch_systems/slurm.py
isabl_cli/data/README.md
isabl_cli/test/__init__.py
isabl_cli/test/utils.py
isabl_cli-2.0.1.dist-info/licenses/LICENSE.md
tests/__init__.py
tests/conftest.py
tests/test_api.py
tests/test_app.py
tests/test_batch_systems.py
tests/test_cli.py
tests/test_commands.py
tests/test_data.py
tests/test_options.py
tests/test_signals.py
tests/test_testutils.py
tests/test_utils.py
tests/test_validators.py
tests/test_version.py
isabl_cli-2.0.1.dist-info/METADATA
isabl_cli-2.0.1.dist-info/WHEEL
isabl_cli-2.0.1.dist-info/entry_points.txt
isabl_cli-2.0.1.dist-info/top_level.txt
isabl_cli-2.0.1.dist-info/RECORD
